django_tables2/__init__.py
django_tables2/config.py
django_tables2/data.py
django_tables2/paginators.py
django_tables2/rows.py
django_tables2/tables.py
django_tables2/utils.py
django_tables2/views.py
django_tables2/columns/__init__.py
django_tables2/columns/base.py
django_tables2/columns/booleancolumn.py
django_tables2/columns/checkboxcolumn.py
django_tables2/columns/datecolumn.py
django_tables2/columns/datetimecolumn.py
django_tables2/columns/emailcolumn.py
django_tables2/columns/filecolumn.py
django_tables2/columns/jsoncolumn.py
django_tables2/columns/linkcolumn.py
django_tables2/columns/manytomanycolumn.py
django_tables2/columns/templatecolumn.py
django_tables2/columns/timecolumn.py
django_tables2/columns/urlcolumn.py
django_tables2/export/__init__.py
django_tables2/export/export.py
django_tables2/export/views.py
django_tables2/locale/cs/LC_MESSAGES/django.mo
django_tables2/locale/cs/LC_MESSAGES/django.po
django_tables2/locale/de/LC_MESSAGES/django.mo
django_tables2/locale/de/LC_MESSAGES/django.po
django_tables2/locale/el/LC_MESSAGES/django.mo
django_tables2/locale/el/LC_MESSAGES/django.po
django_tables2/locale/en/LC_MESSAGES/django.mo
django_tables2/locale/en/LC_MESSAGES/django.po
django_tables2/locale/es/LC_MESSAGES/django.mo
django_tables2/locale/es/LC_MESSAGES/django.po
django_tables2/locale/fa/LC_MESSAGES/django.mo
django_tables2/locale/fa/LC_MESSAGES/django.po
django_tables2/locale/fr/LC_MESSAGES/django.mo
django_tables2/locale/fr/LC_MESSAGES/django.po
django_tables2/locale/hu/LC_MESSAGES/django.mo
django_tables2/locale/hu/LC_MESSAGES/django.po
django_tables2/locale/it/LC_MESSAGES/django.mo
django_tables2/locale/it/LC_MESSAGES/django.po
django_tables2/locale/lt/LC_MESSAGES/django.mo
django_tables2/locale/lt/LC_MESSAGES/django.po
django_tables2/locale/nb/LC_MESSAGES/django.mo
django_tables2/locale/nb/LC_MESSAGES/django.po
django_tables2/locale/nl/LC_MESSAGES/django.mo
django_tables2/locale/nl/LC_MESSAGES/django.po
django_tables2-2.7.4.dist-info/METADATA
django_tables2-2.7.4.dist-info/WHEEL
django_tables2-2.7.4.dist-info/licenses/LICENSE
django_tables2-2.7.4.dist-info/RECORD
