Metadata-Version: 2.4
Name: django-tables2
Version: 2.7.4
Summary: Table/data-grid framework for Django
Project-URL: Changelog, https://github.com/jieter/django-tables2/blob/master/CHANGELOG.md
Project-URL: Documentation, https://django-tables2.readthedocs.io/en/latest/
Project-URL: Homepage, https://github.com/jieter/django-tables2/
Project-URL: Readme, https://github.com/jieter/django-tables2/blob/master/README.md
Author-email: Bradley Ayers <bradley.ayers@gmail.com>, Jan Pieter Waagmeester <jieter@jieter.nl>
License: All changes made to django-tables2 since forking from django-tables
License-File: LICENSE
Classifier: Development Status :: 5 - Production/Stable
Classifier: Environment :: Web Environment
Classifier: Framework :: Django
Classifier: Framework :: Django :: 4.2
Classifier: Framework :: Django :: 5.0
Classifier: Framework :: Django :: 5.1
Classifier: Intended Audience :: Developers
Classifier: License :: OSI Approved :: BSD License
Classifier: Operating System :: OS Independent
Classifier: Programming Language :: Python
Classifier: Programming Language :: Python :: 3
Classifier: Programming Language :: Python :: 3 :: Only
Classifier: Programming Language :: Python :: 3.9
Classifier: Programming Language :: Python :: 3.10
Classifier: Programming Language :: Python :: 3.11
Classifier: Programming Language :: Python :: 3.12
Classifier: Topic :: Internet :: WWW/HTTP
Classifier: Topic :: Software Development :: Libraries
Requires-Python: >=3.9
Requires-Dist: django>=4.2
Provides-Extra: tablib
Requires-Dist: tablib; extra == 'tablib'
